bluebell/__init__.py
bluebell/akn.peg
bluebell/akn.py
bluebell/akn_text.xsl
bluebell/cli.py
bluebell/parser.py
bluebell/types.py
bluebell/xml.py
bluebell_akn-3.1.1.dist-info/LICENSE-LESSER.txt
bluebell_akn-3.1.1.dist-info/LICENSE.txt
bluebell_akn-3.1.1.dist-info/METADATA
bluebell_akn-3.1.1.dist-info/WHEEL
bluebell_akn-3.1.1.dist-info/entry_points.txt
bluebell_akn-3.1.1.dist-info/top_level.txt
bluebell_akn-3.1.1.dist-info/RECORD
