Metadata-Version: 2.2
Name: bluebell-akn
Version: 3.1.1
Summary: Transforms text to and from Akoma Ntoso
Author-email: "Laws.Africa" <info@laws.africa>
License: LGPLv3+
Project-URL: Homepage, https://github.com/laws-africa/bluebell
Project-URL: Bug Tracker, https://github.com/laws-africa/bluebell/issues
Classifier: Development Status :: 5 - Production/Stable
Classifier: Intended Audience :: Developers
Classifier: Topic :: Text Processing
Classifier: Topic :: Text Processing :: Markup :: XML
Classifier: Intended Audience :: Legal Industry
Classifier: License :: OSI Approved :: GNU Lesser General Public License v3 or later (LGPLv3+)
Classifier: Programming Language :: Python
Classifier: Programming Language :: Python :: 3
Requires-Python: >=3.9
License-File: LICENSE-LESSER.txt
License-File: LICENSE.txt
Requires-Dist: cobalt>=9.0.0
Requires-Dist: lxml>=3.4.1
Provides-Extra: test
Requires-Dist: flake8; extra == "test"
